mchammers/__init__.py
mchammers/_version.py
mchammers/_version.pyi
mchammers/hammer.py
mchammers/py.typed
mchammers-0.0.2.dist-info/METADATA
mchammers-0.0.2.dist-info/WHEEL
mchammers-0.0.2.dist-info/licenses/LICENSE
mchammers-0.0.2.dist-info/RECORD
