Metadata-Version: 2.3
Name: mchammers
Version: 0.0.2
Summary: A toy package for sampling posteriors. Our final project for APC 524 at Princeton University.
Project-URL: Homepage, https://github.com/zandalman/mchammers
Project-URL: Bug Tracker, https://github.com/zandalman/mchammers/issues
Project-URL: Discussions, https://github.com/zandalman/mchammers/discussions
Project-URL: Changelog, https://github.com/zandalman/mchammers/releases
Author-email: Zack Andalman <zack.andalman@princeton.edu>, Yue Pan <yue.pan@princeton.edu>, James Sunseri <js7501@princeton.edu>
License: BSD 3-Clause License
Classifier: Development Status :: 1 - Planning
Classifier: Intended Audience :: Developers
Classifier: Intended Audience :: Science/Research
Classifier: License :: OSI Approved :: BSD License
Classifier: Operating System :: OS Independent
Classifier: Programming Language :: Python
Classifier: Programming Language :: Python :: 3
Classifier: Programming Language :: Python :: 3 :: Only
Classifier: Programming Language :: Python :: 3.8
Classifier: Programming Language :: Python :: 3.9
Classifier: Programming Language :: Python :: 3.10
Classifier: Programming Language :: Python :: 3.11
Classifier: Programming Language :: Python :: 3.12
Classifier: Programming Language :: Python :: 3.13
Classifier: Topic :: Scientific/Engineering
Classifier: Typing :: Typed
Requires-Python: >=3.8
Requires-Dist: mpi4py
Requires-Dist: numpy
Provides-Extra: dev
Requires-Dist: mpi4py; extra == 'dev'
Requires-Dist: numpy; extra == 'dev'
Requires-Dist: pytest-cov>=3; extra == 'dev'
Requires-Dist: pytest>=6; extra == 'dev'
Provides-Extra: docs
Requires-Dist: furo>=2023.08.17; extra == 'docs'
Requires-Dist: ipython; extra == 'docs'
Requires-Dist: matplotlib; extra == 'docs'
Requires-Dist: myst-parser>=0.13; extra == 'docs'
Requires-Dist: nbconvert; extra == 'docs'
Requires-Dist: nbsphinx; extra == 'docs'
Requires-Dist: sphinx-autodoc-typehints; extra == 'docs'
Requires-Dist: sphinx-copybutton; extra == 'docs'
Requires-Dist: sphinx-gallery; extra == 'docs'
Requires-Dist: sphinx>=7.0; extra == 'docs'
Provides-Extra: test
Requires-Dist: mpi4py; extra == 'test'
Requires-Dist: numpy; extra == 'test'
Requires-Dist: pytest-cov>=3; extra == 'test'
Requires-Dist: pytest-mpi; extra == 'test'
Requires-Dist: pytest>=6; extra == 'test'
